README.md
setup.cfg
setup.py
sparkxform/__init__.py
sparkxform/date_utils.py
sparkxform/id_generator.py
sparkxform/string_ops.py
sparkxform.egg-info/PKG-INFO
sparkxform.egg-info/SOURCES.txt
sparkxform.egg-info/dependency_links.txt
sparkxform.egg-info/not-zip-safe
sparkxform.egg-info/top_level.txt