Metadata-Version: 2.1
Name: sparkxform
Version: 0.1.0
Summary: Reusable PySpark transformation functions for enterprise-grade ETL pipelines.
Home-page: https://github.com/RanjitM007/sparkxform
Author: Ranjit Maity
Author-email: ranjitmaity95a@gmail.com
License: MIT
Project-URL: Bug Tracker, https://github.com/RanjitM007/sparkxform/issues
Project-URL: Source Code, https://github.com/RanjitM007/sparkxform
Project-URL: Documentation, https://github.com/RanjitM007/sparkxform/wiki
Classifier: Development Status :: 3 - Alpha
Classifier: Intended Audience :: Developers
Classifier: Intended Audience :: Information Technology
Classifier: Topic :: Software Development :: Libraries
Classifier: Topic :: Database :: Front-Ends
Classifier: Programming Language :: Python :: 3
Classifier: License :: OSI Approved :: MIT License
Classifier: Operating System :: OS Independent
Requires-Python: >=3.7
